code_weaver/__init__.py
code_weaver/cli.py
code_weaver/core/__init__.py
code_weaver/core/analyzer.py
code_weaver/core/detector.py
code_weaver/core/fixer.py
code_weaver/healing/__init__.py
code_weaver/healing/applier.py
code_weaver/healing/history.py
code_weaver/issues/__init__.py
code_weaver/issues/base.py
code_weaver/issues/syntax_issues.py
code_weaver/issues/type_errors.py
code_weaver/issues/undefined_vars.py
code_weaver/issues/unused_imports.py
code_weaver/ml/__init__.py
code_weaver/ml/features.py
code_weaver/ml/feedback.py
code_weaver/ml/model.py
code_weaver/watcher/__init__.py
code_weaver/watcher/monitor.py
weave_master-1.0.1.dist-info/licenses/LICENSE
weave_master-1.0.1.dist-info/METADATA
weave_master-1.0.1.dist-info/WHEEL
weave_master-1.0.1.dist-info/entry_points.txt
weave_master-1.0.1.dist-info/top_level.txt
weave_master-1.0.1.dist-info/RECORD
