Metadata-Version: 2.4
Name: weave-master
Version: 1.0.1
Summary: A proactive code healer that predicts and fixes Python issues before they cause problems
Author: Code Weaver Team
License-Expression: MIT
Keywords: python,linter,code-analysis,auto-fix,ml,ast
Classifier: Development Status :: 4 - Beta
Classifier: Environment :: Console
Classifier: Intended Audience :: Developers
Classifier: Operating System :: OS Independent
Classifier: Programming Language :: Python :: 3
Classifier: Programming Language :: Python :: 3.10
Classifier: Programming Language :: Python :: 3.11
Classifier: Programming Language :: Python :: 3.12
Classifier: Topic :: Software Development :: Quality Assurance
Classifier: Topic :: Software Development :: Testing
Requires-Python: >=3.10
License-File: LICENSE
Requires-Dist: click>=8.0
Requires-Dist: watchdog>=3.0
Requires-Dist: scikit-learn>=1.0
Requires-Dist: rich>=13.0
Provides-Extra: dev
Requires-Dist: pytest>=7.0; extra == "dev"
Requires-Dist: pytest-cov>=4.0; extra == "dev"
Dynamic: license-file
